django_minha_lib/__init__.py
django_minha_lib/admin.py
django_minha_lib/apps.py
django_minha_lib/models.py
django_minha_lib/templates/django_minha_lib/pagina_inicial.html
django_minha_lib/templatetags/__init__.py
django_minha_lib/templatetags/minha_lib_tags.py
django_minha_lib/urls.py
django_minha_lib/views.py
django_minha_lib-0.1.5.dist-info/METADATA
django_minha_lib-0.1.5.dist-info/WHEEL
django_minha_lib-0.1.5.dist-info/RECORD
