Metadata-Version: 2.3
Name: django-minha-lib
Version: 0.1.5
Summary: Minha primeira biblioteca Django reutilizável.
License: MIT
Author: Gustavo Rizzo S M de Albuquerque
Author-email: grizzo.albu@gmail.com
Requires-Python: >=3.13,<4.0
Classifier: License :: OSI Approved :: MIT License
Classifier: Programming Language :: Python :: 3
Classifier: Programming Language :: Python :: 3.13
Requires-Dist: django (>=5.2.7,<6.0.0)
